setup.cfg
setup.py
sp.py
smart_pipe/__init__.py
smart_pipe/smart_pipe.py
smart_pipe/test_smart_pipe.py
smart_pipe.egg-info/PKG-INFO
smart_pipe.egg-info/SOURCES.txt
smart_pipe.egg-info/dependency_links.txt
smart_pipe.egg-info/top_level.txt