Metadata-Version: 1.1
Name: smart-pipe
Version: 0.1
Summary: Simple and fast key-value container optimized for sequential read, supporting indexed access and compression
Home-page: http://smart-pipe.readthedocs.io/
Author: Max Lapan
Author-email: max.lapan@gmail.com
License: GPL-v3
Keywords: storage compressed sequential
Platform: UNKNOWN
Classifier: Development Status :: 5 - Production/Stable
Classifier: License :: OSI Approved :: GNU General Public License v3 or later (GPLv3+)
Classifier: Topic :: Software Development :: Libraries
Classifier: Topic :: Database
